{"current":{"temperature":25.5,"feelsLike":31.0,"condition":"Mayormente despejado","windKmh":6.7,"humidity":96},"today":{"date":"2026-07-07","condition":"Llovizna ligera","hi":31.1,"lo":25.5,"rain":65},"next":[{"date":"2026-07-08","condition":"Nublado","hi":32.1,"lo":25.4,"rain":45},{"date":"2026-07-09","condition":"Nublado","hi":32.3,"lo":25.7,"rain":14},{"date":"2026-07-10","condition":"Tormenta con granizo","hi":30.8,"lo":23.2,"rain":61},{"date":"2026-07-11","condition":"Tormenta","hi":32.0,"lo":26.0,"rain":75},{"date":"2026-07-12","condition":"Tormenta con granizo","hi":30.8,"lo":24.8,"rain":90},{"date":"2026-07-13","condition":"Tormenta","hi":29.9,"lo":25.1,"rain":92},{"date":"2026-07-14","condition":"Tormenta","hi":30.2,"lo":24.2,"rain":69}],"updated":"2026-07-07T12:14:56Z","slug":"acapulco"}