{"current":{"temperature":26.4,"feelsLike":33.4,"condition":"Llovizna intensa","windKmh":1.5,"humidity":97},"today":{"date":"2026-06-05","condition":"Chubascos intensos","hi":33.2,"lo":25.2,"rain":90},"next":[{"date":"2026-06-06","condition":"Chubascos","hi":30.8,"lo":24.1,"rain":90},{"date":"2026-06-07","condition":"Chubascos intensos","hi":27.6,"lo":24.1,"rain":86},{"date":"2026-06-08","condition":"Chubascos intensos","hi":25.7,"lo":23.6,"rain":88},{"date":"2026-06-09","condition":"Chubascos","hi":29.1,"lo":24.0,"rain":71},{"date":"2026-06-10","condition":"Chubascos","hi":29.5,"lo":23.8,"rain":34},{"date":"2026-06-11","condition":"Nublado","hi":29.8,"lo":25.1,"rain":31},{"date":"2026-06-12","condition":"Nublado","hi":29.8,"lo":23.9,"rain":43}],"updated":"2026-06-06T02:15:44Z","slug":"acapulco"}