{"current":{"temperature":20.2,"feelsLike":19.0,"condition":"Despejado","windKmh":2.5,"humidity":41},"today":{"date":"2026-05-28","condition":"Nublado","hi":31.7,"lo":18.0,"rain":0},"next":[{"date":"2026-05-29","condition":"Nublado","hi":32.7,"lo":17.7,"rain":0},{"date":"2026-05-30","condition":"Llovizna","hi":33.2,"lo":18.4,"rain":41},{"date":"2026-05-31","condition":"Llovizna","hi":31.6,"lo":18.5,"rain":91},{"date":"2026-06-01","condition":"Llovizna ligera","hi":30.4,"lo":15.9,"rain":59},{"date":"2026-06-02","condition":"Llovizna ligera","hi":31.5,"lo":16.5,"rain":27},{"date":"2026-06-03","condition":"Mayormente despejado","hi":27.9,"lo":14.8,"rain":58},{"date":"2026-06-04","condition":"Mayormente despejado","hi":30.5,"lo":15.6,"rain":53}],"updated":"2026-05-28T13:47:44Z","slug":"aguascalientes"}