{"current":{"temperature":23.6,"feelsLike":23.5,"condition":"Despejado","windKmh":1.8,"humidity":44},"today":{"date":"2026-06-18","condition":"Lluvia ligera","hi":34.4,"lo":20.4,"rain":24},"next":[{"date":"2026-06-19","condition":"Nublado","hi":34.4,"lo":18.3,"rain":10},{"date":"2026-06-20","condition":"Nublado","hi":35.5,"lo":26.4,"rain":2},{"date":"2026-06-21","condition":"Despejado","hi":36.2,"lo":26.6,"rain":2},{"date":"2026-06-22","condition":"Nublado","hi":36.7,"lo":26.9,"rain":9},{"date":"2026-06-23","condition":"Llovizna ligera","hi":37.2,"lo":26.7,"rain":11},{"date":"2026-06-24","condition":"Parcialmente nublado","hi":35.6,"lo":25.8,"rain":11},{"date":"2026-06-25","condition":"Parcialmente nublado","hi":36.9,"lo":27.2,"rain":12}],"updated":"2026-06-18T13:39:27Z","slug":"chihuahua"}