{"current":{"temperature":22.6,"feelsLike":21.9,"condition":"Despejado","windKmh":4.1,"humidity":44},"today":{"date":"2026-06-20","condition":"Despejado","hi":39.2,"lo":21.9,"rain":0},"next":[{"date":"2026-06-21","condition":"Despejado","hi":38.8,"lo":21.6,"rain":0},{"date":"2026-06-22","condition":"Nublado","hi":38.2,"lo":29.9,"rain":0},{"date":"2026-06-23","condition":"Despejado","hi":39.9,"lo":32.0,"rain":0},{"date":"2026-06-24","condition":"Nublado","hi":40.1,"lo":32.1,"rain":8},{"date":"2026-06-25","condition":"Nublado","hi":38.6,"lo":31.5,"rain":32},{"date":"2026-06-26","condition":"Nublado","hi":39.0,"lo":28.4,"rain":32},{"date":"2026-06-27","condition":"Nublado","hi":38.9,"lo":30.0,"rain":14}],"updated":"2026-06-20T11:15:52Z","slug":"ciudad-juarez"}