{"current":{"temperature":20.9,"feelsLike":20.8,"condition":"Parcialmente nublado","windKmh":10.1,"humidity":66},"today":{"date":"2026-07-02","condition":"Llovizna","hi":25.2,"lo":15.6,"rain":98},"next":[{"date":"2026-07-03","condition":"Chubascos","hi":24.7,"lo":15.4,"rain":100},{"date":"2026-07-04","condition":"Llovizna","hi":25.9,"lo":17.2,"rain":76},{"date":"2026-07-05","condition":"Tormenta","hi":22.7,"lo":17.3,"rain":100},{"date":"2026-07-06","condition":"Llovizna ligera","hi":24.4,"lo":17.2,"rain":57},{"date":"2026-07-07","condition":"Llovizna ligera","hi":24.8,"lo":16.2,"rain":76},{"date":"2026-07-08","condition":"Llovizna ligera","hi":23.1,"lo":16.8,"rain":83},{"date":"2026-07-09","condition":"Llovizna ligera","hi":23.5,"lo":16.4,"rain":76}],"updated":"2026-07-03T01:10:32Z","slug":"cuernavaca"}