{"current":{"temperature":25.2,"feelsLike":26.3,"condition":"Mayormente despejado","windKmh":5.3,"humidity":47},"today":{"date":"2026-07-01","condition":"Llovizna ligera","hi":25.2,"lo":17.8,"rain":61},"next":[{"date":"2026-07-02","condition":"Tormenta","hi":24.4,"lo":15.8,"rain":94},{"date":"2026-07-03","condition":"Llovizna ligera","hi":24.8,"lo":15.9,"rain":91},{"date":"2026-07-04","condition":"Llovizna","hi":24.1,"lo":17.0,"rain":93},{"date":"2026-07-05","condition":"Tormenta","hi":22.5,"lo":15.6,"rain":100},{"date":"2026-07-06","condition":"Llovizna ligera","hi":24.4,"lo":16.2,"rain":45},{"date":"2026-07-07","condition":"Nublado","hi":24.4,"lo":16.4,"rain":84},{"date":"2026-07-08","condition":"Llovizna","hi":24.1,"lo":16.7,"rain":88}],"updated":"2026-07-01T21:03:04Z","slug":"cuernavaca"}