{"current":{"temperature":36.2,"feelsLike":36.8,"condition":"Despejado","windKmh":22.5,"humidity":39},"today":{"date":"2026-06-23","condition":"Nublado","hi":40.4,"lo":25.3,"rain":12},"next":[{"date":"2026-06-24","condition":"Tormenta","hi":38.8,"lo":27.0,"rain":9},{"date":"2026-06-25","condition":"Tormenta","hi":38.5,"lo":27.1,"rain":16},{"date":"2026-06-26","condition":"Llovizna ligera","hi":37.0,"lo":28.1,"rain":33},{"date":"2026-06-27","condition":"Chubascos","hi":37.9,"lo":27.7,"rain":22},{"date":"2026-06-28","condition":"Llovizna","hi":38.0,"lo":27.1,"rain":26},{"date":"2026-06-29","condition":"Nublado","hi":36.0,"lo":27.7,"rain":34},{"date":"2026-06-30","condition":"Nublado","hi":38.2,"lo":27.2,"rain":33}],"updated":"2026-06-23T23:47:25Z","slug":"culiacan"}