{"current":{"temperature":18.8,"feelsLike":19.5,"condition":"Nublado","windKmh":6.5,"humidity":80},"today":{"date":"2026-07-05","condition":"Llovizna intensa","hi":27.7,"lo":14.8,"rain":91},"next":[{"date":"2026-07-06","condition":"Tormenta","hi":27.8,"lo":15.4,"rain":97},{"date":"2026-07-07","condition":"Llovizna","hi":25.9,"lo":15.1,"rain":76},{"date":"2026-07-08","condition":"Tormenta con granizo","hi":25.8,"lo":14.8,"rain":71},{"date":"2026-07-09","condition":"Llovizna ligera","hi":25.2,"lo":11.7,"rain":71},{"date":"2026-07-10","condition":"Llovizna","hi":24.8,"lo":14.5,"rain":86},{"date":"2026-07-11","condition":"Llovizna","hi":25.3,"lo":13.7,"rain":86},{"date":"2026-07-12","condition":"Llovizna","hi":24.0,"lo":13.9,"rain":86}],"updated":"2026-07-06T05:49:18Z","slug":"durango"}