{"current":{"temperature":26.3,"feelsLike":25.8,"condition":"Parcialmente nublado","windKmh":12.8,"humidity":36},"today":{"date":"2026-07-02","condition":"Llovizna ligera","hi":26.9,"lo":13.1,"rain":59},"next":[{"date":"2026-07-03","condition":"Llovizna ligera","hi":28.1,"lo":14.9,"rain":85},{"date":"2026-07-04","condition":"Llovizna ligera","hi":28.8,"lo":15.0,"rain":90},{"date":"2026-07-05","condition":"Tormenta","hi":29.0,"lo":17.4,"rain":71},{"date":"2026-07-06","condition":"Llovizna","hi":27.5,"lo":15.8,"rain":81},{"date":"2026-07-07","condition":"Llovizna","hi":26.0,"lo":14.8,"rain":80},{"date":"2026-07-08","condition":"Llovizna","hi":22.1,"lo":13.2,"rain":91},{"date":"2026-07-09","condition":"Llovizna ligera","hi":21.7,"lo":14.0,"rain":91}],"updated":"2026-07-02T20:40:29Z","slug":"durango"}