{"current":{"temperature":19.3,"feelsLike":21.2,"condition":"Nublado","windKmh":3.0,"humidity":86},"today":{"date":"2026-06-08","condition":"Chubascos intensos","hi":27.7,"lo":18.9,"rain":93},"next":[{"date":"2026-06-09","condition":"Llovizna intensa","hi":26.8,"lo":18.3,"rain":92},{"date":"2026-06-10","condition":"Llovizna","hi":25.9,"lo":17.4,"rain":79},{"date":"2026-06-11","condition":"Chubascos","hi":27.4,"lo":18.0,"rain":58},{"date":"2026-06-12","condition":"Chubascos","hi":27.2,"lo":17.4,"rain":73},{"date":"2026-06-13","condition":"Chubascos","hi":26.1,"lo":18.1,"rain":80},{"date":"2026-06-14","condition":"Llovizna","hi":24.7,"lo":17.9,"rain":88},{"date":"2026-06-15","condition":"Llovizna","hi":25.1,"lo":18.5,"rain":86}],"updated":"2026-06-08T13:52:15Z","slug":"guadalajara"}