{"current":{"temperature":24.4,"feelsLike":24.1,"condition":"Despejado","windKmh":6.6,"humidity":46},"today":{"date":"2026-06-07","condition":"Nublado","hi":37.0,"lo":22.2,"rain":0},"next":[{"date":"2026-06-08","condition":"Despejado","hi":36.3,"lo":21.3,"rain":1},{"date":"2026-06-09","condition":"Nublado","hi":38.3,"lo":23.9,"rain":0},{"date":"2026-06-10","condition":"Nublado","hi":37.6,"lo":25.9,"rain":0},{"date":"2026-06-11","condition":"Chubascos","hi":38.2,"lo":27.6,"rain":6},{"date":"2026-06-12","condition":"Nublado","hi":38.2,"lo":27.9,"rain":3},{"date":"2026-06-13","condition":"Parcialmente nublado","hi":41.2,"lo":29.3,"rain":3},{"date":"2026-06-14","condition":"Llovizna ligera","hi":40.2,"lo":29.8,"rain":6}],"updated":"2026-06-07T14:12:51Z","slug":"hermosillo"}