{"updated":"2026-06-21T20:58:04Z","source":"Open-Meteo Forecast API","license":"CC-BY 4.0","count":30,"cities":[{"slug":"cdmx","status":"ok","updated":"2026-06-21T20:54:34Z"},{"slug":"guadalajara","status":"ok","updated":"2026-06-21T20:54:35Z"},{"slug":"monterrey","status":"ok","updated":"2026-06-21T20:54:36Z"},{"slug":"puebla","status":"ok","updated":"2026-06-21T20:54:36Z"},{"slug":"tijuana","status":"ok","updated":"2026-06-21T20:54:37Z"},{"slug":"leon","status":"ok","updated":"2026-06-21T20:54:38Z"},{"slug":"toluca","status":"ok","updated":"2026-06-21T20:54:39Z"},{"slug":"merida","status":"ok","updated":"2026-06-21T20:54:40Z"},{"slug":"queretaro","status":"ok","updated":"2026-06-21T20:54:41Z"},{"slug":"chihuahua","status":"ok","updated":"2026-06-21T20:54:42Z"},{"slug":"hermosillo","status":"ok","updated":"2026-06-21T20:55:44Z"},{"slug":"veracruz","status":"ok","updated":"2026-06-21T20:55:45Z"},{"slug":"cancun","status":"ok","updated":"2026-06-21T20:55:46Z"},{"slug":"acapulco","status":"ok","updated":"2026-06-21T20:55:47Z"},{"slug":"oaxaca","status":"ok","updated":"2026-06-21T20:55:48Z"},{"slug":"morelia","status":"ok","updated":"2026-06-21T20:55:49Z"},{"slug":"aguascalientes","status":"ok","updated":"2026-06-21T20:55:49Z"},{"slug":"saltillo","status":"ok","updated":"2026-06-21T20:56:52Z"},{"slug":"durango","status":"ok","updated":"2026-06-21T20:56:52Z"},{"slug":"zacatecas","status":"ok","updated":"2026-06-21T20:56:53Z"},{"slug":"culiacan","status":"ok","updated":"2026-06-21T20:56:54Z"},{"slug":"mazatlan","status":"ok","updated":"2026-06-21T20:56:55Z"},{"slug":"tampico","status":"ok","updated":"2026-06-21T20:56:56Z"},{"slug":"villahermosa","status":"ok","updated":"2026-06-21T20:56:57Z"},{"slug":"tuxtla-gutierrez","status":"ok","updated":"2026-06-21T20:57:59Z"},{"slug":"pachuca","status":"ok","updated":"2026-06-21T20:58:00Z"},{"slug":"cuernavaca","status":"ok","updated":"2026-06-21T20:58:01Z"},{"slug":"la-paz","status":"ok","updated":"2026-06-21T20:58:02Z"},{"slug":"san-luis-potosi","status":"ok","updated":"2026-06-21T20:58:03Z"},{"slug":"ciudad-juarez","status":"ok","updated":"2026-06-21T20:58:04Z"}]}