{"updated":"2026-07-04T22:29:02Z","source":"Open-Meteo Forecast API","license":"CC-BY 4.0","count":30,"cities":[{"slug":"cdmx","status":"ok","updated":"2026-07-04T22:25:32Z"},{"slug":"guadalajara","status":"ok","updated":"2026-07-04T22:25:33Z"},{"slug":"monterrey","status":"ok","updated":"2026-07-04T22:25:34Z"},{"slug":"puebla","status":"ok","updated":"2026-07-04T22:25:35Z"},{"slug":"tijuana","status":"ok","updated":"2026-07-04T22:25:36Z"},{"slug":"leon","status":"ok","updated":"2026-07-04T22:25:37Z"},{"slug":"toluca","status":"ok","updated":"2026-07-04T22:25:38Z"},{"slug":"merida","status":"ok","updated":"2026-07-04T22:26:40Z"},{"slug":"queretaro","status":"ok","updated":"2026-07-04T22:26:41Z"},{"slug":"chihuahua","status":"ok","updated":"2026-07-04T22:26:42Z"},{"slug":"hermosillo","status":"ok","updated":"2026-07-04T22:26:43Z"},{"slug":"veracruz","status":"ok","updated":"2026-07-04T22:26:44Z"},{"slug":"cancun","status":"ok","updated":"2026-07-04T22:26:45Z"},{"slug":"acapulco","status":"ok","updated":"2026-07-04T22:26:46Z"},{"slug":"oaxaca","status":"ok","updated":"2026-07-04T22:26:47Z"},{"slug":"morelia","status":"ok","updated":"2026-07-04T22:27:49Z"},{"slug":"aguascalientes","status":"ok","updated":"2026-07-04T22:27:50Z"},{"slug":"saltillo","status":"ok","updated":"2026-07-04T22:27:51Z"},{"slug":"durango","status":"ok","updated":"2026-07-04T22:27:52Z"},{"slug":"zacatecas","status":"ok","updated":"2026-07-04T22:27:53Z"},{"slug":"culiacan","status":"ok","updated":"2026-07-04T22:27:54Z"},{"slug":"mazatlan","status":"ok","updated":"2026-07-04T22:27:54Z"},{"slug":"tampico","status":"ok","updated":"2026-07-04T22:27:55Z"},{"slug":"villahermosa","status":"ok","updated":"2026-07-04T22:28:57Z"},{"slug":"tuxtla-gutierrez","status":"ok","updated":"2026-07-04T22:28:58Z"},{"slug":"pachuca","status":"ok","updated":"2026-07-04T22:28:59Z"},{"slug":"cuernavaca","status":"ok","updated":"2026-07-04T22:29:00Z"},{"slug":"la-paz","status":"ok","updated":"2026-07-04T22:29:01Z"},{"slug":"san-luis-potosi","status":"ok","updated":"2026-07-04T22:29:01Z"},{"slug":"ciudad-juarez","status":"ok","updated":"2026-07-04T22:29:02Z"}]}