{"updated":"2026-06-09T20:15:55Z","source":"Open-Meteo Forecast API","license":"CC-BY 4.0","count":30,"cities":[{"slug":"cdmx","status":"ok","updated":"2026-06-09T20:12:29Z"},{"slug":"guadalajara","status":"ok","updated":"2026-06-09T20:12:30Z"},{"slug":"monterrey","status":"ok","updated":"2026-06-09T20:12:31Z"},{"slug":"puebla","status":"ok","updated":"2026-06-09T20:12:31Z"},{"slug":"tijuana","status":"ok","updated":"2026-06-09T20:12:32Z"},{"slug":"leon","status":"ok","updated":"2026-06-09T20:12:33Z"},{"slug":"toluca","status":"ok","updated":"2026-06-09T20:12:34Z"},{"slug":"merida","status":"ok","updated":"2026-06-09T20:12:34Z"},{"slug":"queretaro","status":"ok","updated":"2026-06-09T20:12:35Z"},{"slug":"chihuahua","status":"ok","updated":"2026-06-09T20:13:37Z"},{"slug":"hermosillo","status":"ok","updated":"2026-06-09T20:13:38Z"},{"slug":"veracruz","status":"ok","updated":"2026-06-09T20:13:39Z"},{"slug":"cancun","status":"ok","updated":"2026-06-09T20:13:39Z"},{"slug":"acapulco","status":"ok","updated":"2026-06-09T20:13:40Z"},{"slug":"oaxaca","status":"ok","updated":"2026-06-09T20:13:41Z"},{"slug":"morelia","status":"ok","updated":"2026-06-09T20:13:42Z"},{"slug":"aguascalientes","status":"ok","updated":"2026-06-09T20:13:43Z"},{"slug":"saltillo","status":"ok","updated":"2026-06-09T20:13:43Z"},{"slug":"durango","status":"ok","updated":"2026-06-09T20:14:45Z"},{"slug":"zacatecas","status":"ok","updated":"2026-06-09T20:14:46Z"},{"slug":"culiacan","status":"ok","updated":"2026-06-09T20:14:47Z"},{"slug":"mazatlan","status":"ok","updated":"2026-06-09T20:14:48Z"},{"slug":"tampico","status":"ok","updated":"2026-06-09T20:14:48Z"},{"slug":"villahermosa","status":"ok","updated":"2026-06-09T20:14:49Z"},{"slug":"tuxtla-gutierrez","status":"ok","updated":"2026-06-09T20:14:50Z"},{"slug":"pachuca","status":"ok","updated":"2026-06-09T20:14:51Z"},{"slug":"cuernavaca","status":"ok","updated":"2026-06-09T20:14:52Z"},{"slug":"la-paz","status":"ok","updated":"2026-06-09T20:15:54Z"},{"slug":"san-luis-potosi","status":"ok","updated":"2026-06-09T20:15:54Z"},{"slug":"ciudad-juarez","status":"ok","updated":"2026-06-09T20:15:55Z"}]}