{"updated":"2026-06-17T06:16:33Z","source":"Open-Meteo Forecast API","license":"CC-BY 4.0","count":30,"cities":[{"slug":"cdmx","status":"ok","updated":"2026-06-17T06:13:04Z"},{"slug":"guadalajara","status":"ok","updated":"2026-06-17T06:13:05Z"},{"slug":"monterrey","status":"ok","updated":"2026-06-17T06:13:06Z"},{"slug":"puebla","status":"ok","updated":"2026-06-17T06:13:07Z"},{"slug":"tijuana","status":"ok","updated":"2026-06-17T06:13:08Z"},{"slug":"leon","status":"ok","updated":"2026-06-17T06:13:08Z"},{"slug":"toluca","status":"ok","updated":"2026-06-17T06:13:09Z"},{"slug":"merida","status":"ok","updated":"2026-06-17T06:13:10Z"},{"slug":"queretaro","status":"ok","updated":"2026-06-17T06:13:11Z"},{"slug":"chihuahua","status":"ok","updated":"2026-06-17T06:14:13Z"},{"slug":"hermosillo","status":"ok","updated":"2026-06-17T06:14:14Z"},{"slug":"veracruz","status":"ok","updated":"2026-06-17T06:14:15Z"},{"slug":"cancun","status":"ok","updated":"2026-06-17T06:14:16Z"},{"slug":"acapulco","status":"ok","updated":"2026-06-17T06:14:17Z"},{"slug":"oaxaca","status":"ok","updated":"2026-06-17T06:14:17Z"},{"slug":"morelia","status":"ok","updated":"2026-06-17T06:14:18Z"},{"slug":"aguascalientes","status":"ok","updated":"2026-06-17T06:14:19Z"},{"slug":"saltillo","status":"ok","updated":"2026-06-17T06:14:20Z"},{"slug":"durango","status":"ok","updated":"2026-06-17T06:14:21Z"},{"slug":"zacatecas","status":"ok","updated":"2026-06-17T06:15:23Z"},{"slug":"culiacan","status":"ok","updated":"2026-06-17T06:15:24Z"},{"slug":"mazatlan","status":"ok","updated":"2026-06-17T06:15:25Z"},{"slug":"tampico","status":"ok","updated":"2026-06-17T06:15:26Z"},{"slug":"villahermosa","status":"ok","updated":"2026-06-17T06:15:27Z"},{"slug":"tuxtla-gutierrez","status":"ok","updated":"2026-06-17T06:15:27Z"},{"slug":"pachuca","status":"ok","updated":"2026-06-17T06:15:28Z"},{"slug":"cuernavaca","status":"ok","updated":"2026-06-17T06:15:29Z"},{"slug":"la-paz","status":"ok","updated":"2026-06-17T06:15:30Z"},{"slug":"san-luis-potosi","status":"ok","updated":"2026-06-17T06:15:31Z"},{"slug":"ciudad-juarez","status":"ok","updated":"2026-06-17T06:16:33Z"}]}