{"current":{"temperature":35.7,"feelsLike":40.2,"condition":"Despejado","windKmh":13.3,"humidity":41},"today":{"date":"2026-07-05","condition":"Nublado","hi":39.5,"lo":22.6,"rain":1},"next":[{"date":"2026-07-06","condition":"Nublado","hi":37.5,"lo":22.9,"rain":4},{"date":"2026-07-07","condition":"Nublado","hi":37.0,"lo":24.1,"rain":3},{"date":"2026-07-08","condition":"Nublado","hi":36.3,"lo":24.9,"rain":2},{"date":"2026-07-09","condition":"Llovizna ligera","hi":36.3,"lo":24.6,"rain":16},{"date":"2026-07-10","condition":"Llovizna ligera","hi":33.5,"lo":25.2,"rain":21},{"date":"2026-07-11","condition":"Llovizna ligera","hi":32.9,"lo":26.0,"rain":25},{"date":"2026-07-12","condition":"Despejado","hi":35.3,"lo":27.4,"rain":9}],"updated":"2026-07-05T18:36:32Z","slug":"la-paz"}