{"current":{"temperature":28.8,"feelsLike":32.4,"condition":"Nublado","windKmh":15.1,"humidity":62},"today":{"date":"2026-06-08","condition":"Nublado","hi":28.9,"lo":25.2,"rain":0},"next":[{"date":"2026-06-09","condition":"Nublado","hi":29.6,"lo":25.7,"rain":22},{"date":"2026-06-10","condition":"Lluvia ligera","hi":26.8,"lo":25.5,"rain":59},{"date":"2026-06-11","condition":"Llovizna ligera","hi":28.4,"lo":25.0,"rain":37},{"date":"2026-06-12","condition":"Nublado","hi":29.5,"lo":25.8,"rain":41},{"date":"2026-06-13","condition":"Llovizna ligera","hi":29.2,"lo":25.3,"rain":29},{"date":"2026-06-14","condition":"Llovizna ligera","hi":28.6,"lo":24.1,"rain":27},{"date":"2026-06-15","condition":"Llovizna ligera","hi":29.0,"lo":25.2,"rain":35}],"updated":"2026-06-08T21:14:22Z","slug":"mazatlan"}