{"current":{"temperature":17.1,"feelsLike":18.9,"condition":"Parcialmente nublado","windKmh":2.2,"humidity":94},"today":{"date":"2026-07-20","condition":"Chubascos","hi":25.6,"lo":13.4,"rain":84},"next":[{"date":"2026-07-21","condition":"Llovizna ligera","hi":25.3,"lo":14.2,"rain":59},{"date":"2026-07-22","condition":"Llovizna","hi":24.8,"lo":13.0,"rain":68},{"date":"2026-07-23","condition":"Llovizna ligera","hi":26.2,"lo":14.4,"rain":37},{"date":"2026-07-24","condition":"Parcialmente nublado","hi":26.8,"lo":14.7,"rain":20},{"date":"2026-07-25","condition":"Llovizna ligera","hi":25.9,"lo":14.4,"rain":46},{"date":"2026-07-26","condition":"Llovizna ligera","hi":24.7,"lo":13.6,"rain":75},{"date":"2026-07-27","condition":"Llovizna ligera","hi":24.9,"lo":12.0,"rain":67}],"updated":"2026-07-21T04:42:59Z","slug":"morelia"}