{"current":{"temperature":16.0,"feelsLike":16.1,"condition":"Despejado","windKmh":5.4,"humidity":83},"today":{"date":"2026-07-20","condition":"Mayormente despejado","hi":28.3,"lo":13.0,"rain":0},"next":[{"date":"2026-07-21","condition":"Parcialmente nublado","hi":28.4,"lo":12.8,"rain":29},{"date":"2026-07-22","condition":"Llovizna ligera","hi":28.4,"lo":12.4,"rain":22},{"date":"2026-07-23","condition":"Llovizna ligera","hi":28.6,"lo":13.2,"rain":35},{"date":"2026-07-24","condition":"Llovizna ligera","hi":28.2,"lo":12.0,"rain":37},{"date":"2026-07-25","condition":"Nublado","hi":29.1,"lo":12.9,"rain":35},{"date":"2026-07-26","condition":"Nublado","hi":28.9,"lo":13.9,"rain":37},{"date":"2026-07-27","condition":"Llovizna ligera","hi":27.3,"lo":16.0,"rain":82}],"updated":"2026-07-21T04:42:58Z","slug":"oaxaca"}