{"current":{"temperature":20.6,"feelsLike":21.4,"condition":"Mayormente despejado","windKmh":3.7,"humidity":66},"today":{"date":"2026-05-25","condition":"Lluvia ligera","hi":28.8,"lo":17.6,"rain":92},"next":[{"date":"2026-05-26","condition":"Llovizna ligera","hi":30.0,"lo":16.8,"rain":73},{"date":"2026-05-27","condition":"Chubascos intensos","hi":31.0,"lo":17.5,"rain":84},{"date":"2026-05-28","condition":"Llovizna ligera","hi":28.0,"lo":16.9,"rain":95}],"updated":"2026-05-26T02:16:09Z","slug":"oaxaca"}