{"current":{"temperature":22.3,"feelsLike":22.9,"condition":"Nublado","windKmh":9.3,"humidity":66},"today":{"date":"2026-06-04","condition":"Lluvia","hi":25.8,"lo":17.2,"rain":100},"next":[{"date":"2026-06-05","condition":"Lluvia","hi":26.1,"lo":16.6,"rain":100},{"date":"2026-06-06","condition":"Lluvia ligera","hi":26.2,"lo":16.9,"rain":98},{"date":"2026-06-07","condition":"Lluvia","hi":26.6,"lo":17.5,"rain":100},{"date":"2026-06-08","condition":"Chubascos intensos","hi":22.0,"lo":16.1,"rain":96},{"date":"2026-06-09","condition":"Llovizna intensa","hi":23.9,"lo":17.1,"rain":73},{"date":"2026-06-10","condition":"Chubascos","hi":23.1,"lo":16.9,"rain":86},{"date":"2026-06-11","condition":"Chubascos","hi":23.3,"lo":15.8,"rain":76}],"updated":"2026-06-04T22:01:32Z","slug":"oaxaca"}