{"current":{"temperature":12.7,"feelsLike":12.7,"condition":"Nublado","windKmh":4.8,"humidity":96},"today":{"date":"2026-06-12","condition":"Llovizna","hi":20.4,"lo":11.8,"rain":84},"next":[{"date":"2026-06-13","condition":"Lluvia","hi":20.8,"lo":11.5,"rain":98},{"date":"2026-06-14","condition":"Llovizna ligera","hi":22.6,"lo":12.1,"rain":78},{"date":"2026-06-15","condition":"Llovizna ligera","hi":22.8,"lo":13.2,"rain":53},{"date":"2026-06-16","condition":"Llovizna","hi":21.9,"lo":13.0,"rain":63},{"date":"2026-06-17","condition":"Lluvia ligera","hi":21.7,"lo":12.8,"rain":82},{"date":"2026-06-18","condition":"Lluvia ligera","hi":22.1,"lo":12.0,"rain":85},{"date":"2026-06-19","condition":"Chubascos intensos","hi":22.5,"lo":12.6,"rain":76}],"updated":"2026-06-12T08:04:50Z","slug":"pachuca"}