{"current":{"temperature":20.6,"feelsLike":22.5,"condition":"Tormenta","windKmh":10.7,"humidity":70},"today":{"date":"2026-06-15","condition":"Tormenta","hi":22.2,"lo":13.8,"rain":95},"next":[{"date":"2026-06-16","condition":"Tormenta","hi":21.7,"lo":13.3,"rain":98},{"date":"2026-06-17","condition":"Tormenta","hi":20.4,"lo":14.5,"rain":94},{"date":"2026-06-18","condition":"Tormenta","hi":21.6,"lo":14.2,"rain":95},{"date":"2026-06-19","condition":"Tormenta","hi":22.3,"lo":15.0,"rain":90},{"date":"2026-06-20","condition":"Llovizna ligera","hi":23.7,"lo":13.0,"rain":70},{"date":"2026-06-21","condition":"Llovizna ligera","hi":22.1,"lo":12.4,"rain":54},{"date":"2026-06-22","condition":"Llovizna","hi":21.7,"lo":12.6,"rain":64}],"updated":"2026-06-15T18:52:28Z","slug":"puebla"}