{"current":{"temperature":17.2,"feelsLike":18.1,"condition":"Nublado","windKmh":2.8,"humidity":83},"today":{"date":"2026-06-08","condition":"Chubascos intensos","hi":23.1,"lo":14.4,"rain":96},"next":[{"date":"2026-06-09","condition":"Chubascos intensos","hi":23.2,"lo":14.4,"rain":92},{"date":"2026-06-10","condition":"Llovizna intensa","hi":23.6,"lo":12.8,"rain":89},{"date":"2026-06-11","condition":"Chubascos","hi":22.4,"lo":13.3,"rain":99},{"date":"2026-06-12","condition":"Chubascos intensos","hi":21.2,"lo":11.9,"rain":100},{"date":"2026-06-13","condition":"Chubascos intensos","hi":21.2,"lo":12.8,"rain":97},{"date":"2026-06-14","condition":"Llovizna","hi":20.6,"lo":13.4,"rain":86},{"date":"2026-06-15","condition":"Llovizna","hi":19.8,"lo":13.4,"rain":82}],"updated":"2026-06-08T13:52:17Z","slug":"puebla"}