{"current":{"temperature":24.0,"feelsLike":25.3,"condition":"Despejado","windKmh":5.3,"humidity":42},"today":{"date":"2026-06-26","condition":"Llovizna ligera","hi":27.9,"lo":14.9,"rain":22},"next":[{"date":"2026-06-27","condition":"Llovizna ligera","hi":28.8,"lo":14.3,"rain":41},{"date":"2026-06-28","condition":"Llovizna ligera","hi":28.3,"lo":15.4,"rain":84},{"date":"2026-06-29","condition":"Tormenta con granizo","hi":25.9,"lo":15.3,"rain":99},{"date":"2026-06-30","condition":"Tormenta con granizo","hi":20.7,"lo":15.6,"rain":100},{"date":"2026-07-01","condition":"Tormenta con granizo","hi":20.5,"lo":15.9,"rain":94},{"date":"2026-07-02","condition":"Tormenta","hi":20.5,"lo":15.3,"rain":73},{"date":"2026-07-03","condition":"Tormenta","hi":22.3,"lo":15.3,"rain":69}],"updated":"2026-06-26T17:08:59Z","slug":"san-luis-potosi"}