{"current":{"temperature":30.5,"feelsLike":36.0,"condition":"Mayormente despejado","windKmh":13.1,"humidity":70},"today":{"date":"2026-06-10","condition":"Chubascos","hi":31.6,"lo":24.9,"rain":92},"next":[{"date":"2026-06-11","condition":"Chubascos intensos","hi":30.9,"lo":24.9,"rain":90},{"date":"2026-06-12","condition":"Chubascos violentos","hi":30.3,"lo":24.8,"rain":100},{"date":"2026-06-13","condition":"Llovizna intensa","hi":30.1,"lo":24.8,"rain":96},{"date":"2026-06-14","condition":"Chubascos","hi":30.8,"lo":25.6,"rain":77},{"date":"2026-06-15","condition":"Chubascos","hi":31.4,"lo":25.2,"rain":69},{"date":"2026-06-16","condition":"Tormenta","hi":32.5,"lo":25.6,"rain":65},{"date":"2026-06-17","condition":"Llovizna","hi":30.7,"lo":25.7,"rain":59}],"updated":"2026-06-10T21:18:36Z","slug":"tampico"}