{"current":{"temperature":27.7,"feelsLike":34.4,"condition":"Tormenta","windKmh":6.5,"humidity":93},"today":{"date":"2026-06-22","condition":"Tormenta con granizo","hi":32.2,"lo":27.4,"rain":78},"next":[{"date":"2026-06-23","condition":"Tormenta con granizo","hi":30.3,"lo":25.1,"rain":95},{"date":"2026-06-24","condition":"Tormenta","hi":31.1,"lo":24.4,"rain":86},{"date":"2026-06-25","condition":"Tormenta con granizo","hi":30.1,"lo":23.9,"rain":81},{"date":"2026-06-26","condition":"Tormenta con granizo","hi":30.7,"lo":25.8,"rain":67},{"date":"2026-06-27","condition":"Tormenta con granizo","hi":30.9,"lo":26.2,"rain":63},{"date":"2026-06-28","condition":"Tormenta con granizo","hi":29.9,"lo":24.2,"rain":80},{"date":"2026-06-29","condition":"Tormenta con granizo","hi":29.4,"lo":23.3,"rain":69}],"updated":"2026-06-22T08:35:17Z","slug":"tampico"}