{"current":{"temperature":17.3,"feelsLike":19.5,"condition":"Parcialmente nublado","windKmh":2.5,"humidity":99},"today":{"date":"2026-06-14","condition":"Niebla","hi":22.9,"lo":16.1,"rain":2},"next":[{"date":"2026-06-15","condition":"Nublado","hi":22.3,"lo":17.5,"rain":1},{"date":"2026-06-16","condition":"Llovizna ligera","hi":26.1,"lo":18.9,"rain":1},{"date":"2026-06-17","condition":"Despejado","hi":25.8,"lo":18.8,"rain":1},{"date":"2026-06-18","condition":"Despejado","hi":25.3,"lo":18.2,"rain":0},{"date":"2026-06-19","condition":"Mayormente despejado","hi":22.8,"lo":17.4,"rain":0},{"date":"2026-06-20","condition":"Mayormente despejado","hi":21.7,"lo":17.1,"rain":0},{"date":"2026-06-21","condition":"Mayormente despejado","hi":21.4,"lo":16.4,"rain":1}],"updated":"2026-06-14T09:42:14Z","slug":"tijuana"}