{"current":{"temperature":22.0,"feelsLike":26.4,"condition":"Nublado","windKmh":1.3,"humidity":96},"today":{"date":"2026-06-23","condition":"Tormenta","hi":33.0,"lo":21.5,"rain":100},"next":[{"date":"2026-06-24","condition":"Tormenta","hi":34.0,"lo":23.0,"rain":100},{"date":"2026-06-25","condition":"Llovizna","hi":33.2,"lo":23.8,"rain":82},{"date":"2026-06-26","condition":"Llovizna ligera","hi":33.0,"lo":21.5,"rain":98},{"date":"2026-06-27","condition":"Tormenta","hi":32.7,"lo":22.4,"rain":100},{"date":"2026-06-28","condition":"Tormenta con granizo","hi":31.4,"lo":20.8,"rain":96},{"date":"2026-06-29","condition":"Nublado","hi":32.3,"lo":21.1,"rain":39},{"date":"2026-06-30","condition":"Llovizna ligera","hi":33.4,"lo":22.1,"rain":61}],"updated":"2026-06-23T11:33:59Z","slug":"tuxtla-gutierrez"}