{"current":{"temperature":22.2,"feelsLike":25.8,"condition":"Despejado","windKmh":1.7,"humidity":87},"today":{"date":"2026-06-20","condition":"Tormenta","hi":36.4,"lo":22.2,"rain":100},"next":[{"date":"2026-06-21","condition":"Tormenta","hi":34.7,"lo":21.0,"rain":98},{"date":"2026-06-22","condition":"Tormenta con granizo","hi":34.7,"lo":21.5,"rain":96},{"date":"2026-06-23","condition":"Tormenta","hi":31.0,"lo":20.9,"rain":92},{"date":"2026-06-24","condition":"Tormenta","hi":30.8,"lo":22.6,"rain":97},{"date":"2026-06-25","condition":"Tormenta","hi":30.6,"lo":22.0,"rain":92},{"date":"2026-06-26","condition":"Llovizna ligera","hi":31.3,"lo":21.1,"rain":78},{"date":"2026-06-27","condition":"Tormenta","hi":32.2,"lo":21.8,"rain":100}],"updated":"2026-06-20T12:09:37Z","slug":"tuxtla-gutierrez"}