{"current":{"temperature":12.6,"feelsLike":11.1,"condition":"Despejado","windKmh":14.3,"humidity":95},"today":{"date":"2026-06-18","condition":"Chubascos","hi":23.6,"lo":12.7,"rain":83},"next":[{"date":"2026-06-19","condition":"Tormenta","hi":23.6,"lo":13.1,"rain":100},{"date":"2026-06-20","condition":"Tormenta con granizo","hi":22.5,"lo":13.1,"rain":100},{"date":"2026-06-21","condition":"Tormenta con granizo","hi":20.6,"lo":13.4,"rain":100},{"date":"2026-06-22","condition":"Tormenta","hi":22.3,"lo":13.3,"rain":82},{"date":"2026-06-23","condition":"Llovizna ligera","hi":23.5,"lo":11.7,"rain":27},{"date":"2026-06-24","condition":"Nublado","hi":21.4,"lo":11.2,"rain":33},{"date":"2026-06-25","condition":"Llovizna ligera","hi":20.4,"lo":9.9,"rain":39}],"updated":"2026-06-18T11:47:20Z","slug":"zacatecas"}